Metadata-Version: 1.1
Name: ymcalculator
Version: 0.0.1
Summary: The very zimple calculato
Home-page: UNKNOWN
Author: Yam
Author-email: ymgchbrtv0095@gmail.com
License: MIT
Keywords: calculator
Platform: UNKNOWN
Classifier: Development Status :: 5 - Production/Stable
Classifier: Intended Audience :: Education
Classifier: Operating System :: POSIX :: Linux
Classifier: License :: OSI Approved :: MIT License
Classifier: Programming Language :: Python :: 2.7
Classifier: Programming Language :: Python :: 3
